rufus-0.1.0.dist-info/METADATA
rufus-0.1.0.dist-info/WHEEL
rufus/__init__.py
rufus/documents.py
rufus/models/__init__.py
rufus/models/_base.py
rufus/models/huggingface.py
rufus/models/openai.py
rufus/models/sentence_transformers.py
rufus/text/__init__.py
rufus/text/bm25.py
rufus/tools.py
rufus/vector/__init__.py
rufus/vector/_base.py
rufus/vector/annoy.py
rufus/vector/voyager.py
rufus-0.1.0.dist-info/RECORD
